bytedance_product_policy_framework/__init__.py
bytedance_product_policy_framework-0.0.1.dist-info/METADATA
bytedance_product_policy_framework-0.0.1.dist-info/WHEEL
bytedance_product_policy_framework-0.0.1.dist-info/top_level.txt
bytedance_product_policy_framework-0.0.1.dist-info/RECORD
